LICENSE
README.md
setup.py
Adam_Serial_for_controller.egg-info/PKG-INFO
Adam_Serial_for_controller.egg-info/SOURCES.txt
Adam_Serial_for_controller.egg-info/dependency_links.txt
Adam_Serial_for_controller.egg-info/requires.txt
Adam_Serial_for_controller.egg-info/top_level.txt
Serial/__init__.py
Serial/serialPi.py
Serial/serial_aaarch64.so
Serial/serial_armv71.so