Metadata-Version: 2.1
Name: Adam-Serial-for-controller
Version: 0.2.0
Summary: Python library for data exchange with adam controller
Home-page: https://github.com/Adam-Software/Serial-for-controller
Author: vertigra
Author-email: a@nesterof.com
License: MIT
Platform: UNKNOWN
Classifier: Development Status :: 3 - Alpha
Classifier: License :: OSI Approved :: MIT License
Classifier: Operating System :: POSIX :: Other
Classifier: Programming Language :: C
Classifier: Programming Language :: Python :: 3
License-File: LICENSE
